LICENSE.txt
MANIFEST.in
README.md
requirements.txt
setup.py
ImmuneDB.egg-info/PKG-INFO
ImmuneDB.egg-info/SOURCES.txt
ImmuneDB.egg-info/dependency_links.txt
ImmuneDB.egg-info/requires.txt
ImmuneDB.egg-info/top_level.txt
bin/immunedb_admin
bin/immunedb_clone_import
bin/immunedb_clone_pressure
bin/immunedb_clone_stats
bin/immunedb_clone_trees
bin/immunedb_clones
bin/immunedb_collapse
bin/immunedb_export
bin/immunedb_genotype
bin/immunedb_identify
bin/immunedb_import
bin/immunedb_local_align
bin/immunedb_metadata
bin/immunedb_modify
bin/immunedb_rest
bin/immunedb_sample_stats
bin/immunedb_sql
bin/run_tigger
immunedb/__init__.py
immunedb/aggregation/__init__.py
immunedb/aggregation/clone_stats.py
immunedb/aggregation/clones.py
immunedb/aggregation/collapse.py
immunedb/aggregation/sample_stats.py
immunedb/api/__init__.py
immunedb/api/jobs.py
immunedb/api/queries.py
immunedb/api/rest_service.py
immunedb/common/__init__.py
immunedb/common/baseline.py
immunedb/common/config.py
immunedb/common/models.py
immunedb/common/modification_log.py
immunedb/common/modify.py
immunedb/common/mutations.py
immunedb/exporting/__init__.py
immunedb/exporting/genbank.py
immunedb/exporting/samples.py
immunedb/exporting/selection.py
immunedb/exporting/sequences.py
immunedb/exporting/tsv_writer.py
immunedb/exporting/writer.py
immunedb/exporting/clones/__init__.py
immunedb/exporting/clones/listing.py
immunedb/exporting/clones/overlap.py
immunedb/identification/__init__.py
immunedb/identification/anchor.py
immunedb/identification/genes.py
immunedb/identification/identify.py
immunedb/identification/local_align.py
immunedb/identification/metadata.py
immunedb/identification/vdj_sequence.py
immunedb/importing/__init__.py
immunedb/importing/alignments.py
immunedb/importing/clones.py
immunedb/trees/__init__.py
immunedb/trees/clearcut.py
immunedb/util/__init__.py
immunedb/util/admin.py
immunedb/util/concurrent.py
immunedb/util/funcs.py
immunedb/util/hyper.py
immunedb/util/log.py
immunedb/util/lookups.py
lib/dnautils.c