Metadata-Version: 2.1
Name: ImmuneDB
Version: 0.29.3
Summary: A system for the analysis and exploration of high-throughput
Home-page: https://github.com/arosenfeld/immunedb
Author: Aaron M. Rosenfeld
Author-email: aaron.rosenfeld@pennmedicine.upenn.edu
License: LICENSE.txt
Platform: UNKNOWN
Classifier: Development Status :: 5 - Production/Stable
Classifier: Environment :: Console
Classifier: Intended Audience :: Science/Research
Classifier: Natural Language :: English
Classifier: Programming Language :: Python :: 3
Classifier: Topic :: Scientific/Engineering :: Bio-Informatics
